filesystems/__init__.py
filesystems/_path.py
filesystems/click.py
filesystems/common.py
filesystems/exceptions.py
filesystems/interfaces.py
filesystems/memory.py
filesystems/native.py
filesystems/tests/__init__.py
filesystems/tests/common.py
filesystems/tests/test_click.py
filesystems/tests/test_memory.py
filesystems/tests/test_native.py
filesystems/tests/test_path.py
filesystems-0.26.0.dist-info/COPYING
filesystems-0.26.0.dist-info/METADATA
filesystems-0.26.0.dist-info/WHEEL
filesystems-0.26.0.dist-info/top_level.txt
filesystems-0.26.0.dist-info/RECORD
